HDLTex/BuildModel.py
HDLTex/Data_helper.py
HDLTex/Download_Glove.py
HDLTex/HDLTex.py
HDLTex/WOS_input.py
HDLTex-1.0.5.dist-info/METADATA
HDLTex-1.0.5.dist-info/RECORD
HDLTex-1.0.5.dist-info/WHEEL
HDLTex-1.0.5.dist-info/top_level.txt
