Metadata-Version: 2.1
Name: HDLTex
Version: 1.0.5
Summary: HDLTex: Hierarchical Deep Learning for Text Classification
Home-page: https://github.com/kk7nc/HDLTex
Author: Kamran Kowsari
Author-email: kk7nc@virginia.edu
License: UNKNOWN
Platform: UNKNOWN
Classifier: Programming Language :: Python :: 3.6
Classifier: Programming Language :: Python :: 3.5
Classifier: Environment :: Console
Classifier: Intended Audience :: Science/Research
Classifier: License :: OSI Approved :: MIT License
Classifier: Operating System :: OS Independent
Classifier: Topic :: Scientific/Engineering :: Artificial Intelligence
Classifier: Topic :: Scientific/Engineering :: Information Analysis
Classifier: Topic :: Text Processing :: Linguistic
Requires-Dist: matplotlib (>=2.1.2)
Requires-Dist: numpy (>=1.12.1)
Requires-Dist: pandas (>=0.22.0)
Requires-Dist: scipy
Requires-Dist: tensorflow-gpu
Requires-Dist: keras (>=2.0.9)
Requires-Dist: scikit-learn (>=0.19.0)
Requires-Dist: nltk (>=3.2.4)
